confready/__init__.py
confready/cli.py
confready/frontend/README.md
confready/frontend/package-lock.json
confready/frontend/package.json
confready/frontend/tailwind.config.js
confready/frontend/public/confready.png
confready/frontend/public/favicon.ico
confready/frontend/public/index.html
confready/frontend/public/logo192.png
confready/frontend/public/logo512.png
confready/frontend/public/manifest.json
confready/frontend/public/robots.txt
confready/frontend/src/index.css
confready/frontend/src/index.js
confready/frontend/src/logo.svg
confready/frontend/src/reportWebVitals.js
confready/frontend/src/setupTests.js
confready/frontend/src/store.js
confready/frontend/src/assets/confready.png
confready/frontend/src/components/Home/Home.js
confready/frontend/src/components/Question/Question.js
confready/frontend/src/components/Sidebar/Sidebar.js
confready/server/README.md
confready/server/acl_checklist_prompts.py
confready/server/app.py
confready/server/neurips_a_checklist_prompts.py
confready/server/neurips_b_checklist_prompts.py
confready/server/process_file.py
confready/server/__pycache__/acl_checklist_prompts.cpython-312.pyc
confready/server/__pycache__/neurips_a_checklist_prompts.cpython-312.pyc
confready/server/__pycache__/neurips_b_checklist_prompts.cpython-312.pyc
confready/server/__pycache__/process_file.cpython-312.pyc
confready-0.0.3.dist-info/METADATA
confready-0.0.3.dist-info/WHEEL
confready-0.0.3.dist-info/entry_points.txt
confready-0.0.3.dist-info/top_level.txt
confready-0.0.3.dist-info/RECORD
