Metadata-Version: 2.4
Name: confready
Version: 0.0.3
Home-page: https://github.com/gtfintechlab/ConfReady
Author: Michael Galarnyk, Rutwik Routu, Vidhyakshaya Kannan, Kosha Bheda, Prasun Banerjee, Agam Shah and Sudheer Chava
License: AGPL-3.0
Classifier: Programming Language :: Python :: 3
Classifier: License :: OSI Approved :: GNU Affero General Public License v3
Classifier: Operating System :: OS Independent
Classifier: Topic :: Scientific/Engineering :: Artificial Intelligence
Classifier: Intended Audience :: Science/Research
Requires-Python: >=3.11
Requires-Dist: flask
Requires-Dist: flask_cors
Requires-Dist: jupyterlab
Requires-Dist: llama-index
Requires-Dist: llama-index-embeddings-together
Requires-Dist: matplotlib
Requires-Dist: openai
Requires-Dist: pylatexenc
Requires-Dist: python-dotenv
Requires-Dist: together
Requires-Dist: scikit-learn
Requires-Dist: bm25s
Requires-Dist: json-repair
Dynamic: author
Dynamic: classifier
Dynamic: description
Dynamic: description-content-type
Dynamic: home-page
Dynamic: license
Dynamic: requires-dist
Dynamic: requires-python
